build_a_cog-0.0.4.dist-info/METADATA
build_a_cog-0.0.4.dist-info/WHEEL
build_a_cog-0.0.4.dist-info/license_files/LICENSE
build_a_cog/__init__.py
build_a_cog/builder.py
build_a_cog/build_a_cog.cpython-311-darwin.so
build_a_cog-0.0.4.dist-info/RECORD
