Metadata-Version: 2.3
Name: build_a_cog
Version: 0.0.4
Classifier: Programming Language :: Python :: 3
Classifier: License :: OSI Approved :: MIT License
Classifier: Operating System :: OS Independent
Requires-Dist: panda3d ~=1.10.11
License-File: LICENSE
Summary: A Python package to make the creation of Cog actors easier!
Author-email: Vhou-Atroph <vhouatroph@proton.me>
Requires-Python: >=3.11
Project-URL: Homepage, https://github.com/Vhou-Atroph/build-a-cog
Project-URL: Bug Tracker, https://github.com/Vhou-Atroph/build-a-cog/issues
